MANIFEST.in
README.md
copyright.txt
requirements.dev.txt
requirements.txt
setup.cfg
setup.py
scripts/sb
src/frappe.egg-info/PKG-INFO
src/frappe.egg-info/SOURCES.txt
src/frappe.egg-info/dependency_links.txt
src/frappe.egg-info/requires.txt
src/frappe.egg-info/top_level.txt
src/recommendation/__init__.py
src/recommendation/backends.py
src/recommendation/core.py
src/recommendation/decorators.py
src/recommendation/models.py
src/recommendation/urls.py
src/recommendation/util.py
src/recommendation/wsgi.py
src/recommendation/api/__init__.py
src/recommendation/api/urls.py
src/recommendation/api/views.py
src/recommendation/data/big_url.txt
src/recommendation/data/info.txt
src/recommendation/data/urls_all.txt
src/recommendation/data/urls_mt_3.txt
src/recommendation/data/user/0000389d24eb79b0970d3baccaff7736fd2aebc7eee5d0615779a2d3dd5824aa.json
src/recommendation/data/user/0001fd3f8d5b0092487f3cdaa7ac3d16f7511fc9fb715be6bfeff21d79ca0ec7.json
src/recommendation/data/user/000740a0fd562f468d8a13efa5f8931d4ec642ea615aa81817f2455ea58be39c.json
src/recommendation/data/user/000f02ca1a0ed44ca0d8875262da3cb157048e77ae22b00fb153b9d864cb2399.json
src/recommendation/data/user/00231cf699a8a43b8bfa0edb0ed11225792713e942dc6086d79398dfa36f60d5.json
src/recommendation/data/user/002c50b7dae6a30ded5372ae1033da43bba90b4d477733375994791e758fbee0.json
src/recommendation/data/user/0031987a4a614ec20c974b7b529460d0d6e4ab7f7b4a66078879f9a3a9ac02d3.json
src/recommendation/data/user/0033597455692156e68dfdc2fc3936595b560834d1a0d68d8606e23779f454e1.json
src/recommendation/data/user/00360cca7ccdb1464cca0e42cef52753698295b4c148f86d2fa74431001477a8.json
src/recommendation/data/user/003b6424db7d4abf8b3b7ff4cc3e36a12dded2cca7f0486a3def2d3a613383b6.json
src/recommendation/data/user/003bbeada921130fe22e9d38d15f7309481740a657468b28d5c1e0542c3bfee1.json
src/recommendation/data/user/0040e721c05603028bde295a6a0425f96438a31efe65bbc1e177bc284f8414c8.json
src/recommendation/data/user/00434600ac4464c2ac5597e5fdbbf4daf6f6ff8d45d1a0bfede28b4dc4f28759.json
src/recommendation/data/user/00459b512f38088dab3fed4dbeaaa13e6c970e8aef79aeeb3e1a09c877633a60.json
