Metadata-Version: 1.1
Name: frappe
Version: 2.1.4
Summary: Frappe is recommendation system backend.
Home-page: https://github.com/grafos-ml/frappe
Author: Linas Baltrunas
Author-email: linas@tid.com
License: copyright.txt
Download-URL: https://github.com/grafos-ml/frappe/archive/v2.1.4.tar.gz
Keywords: recommendation
Platform: UNKNOWN
